libraries/__init__.py
libraries/copy.py
libraries/definitions.py
libraries/neurons.py
libraries/otup.py
libraries/otup2.py
libraries/snippets.py
latex_ml_helper-0.1.0.dist-info/METADATA
latex_ml_helper-0.1.0.dist-info/WHEEL
latex_ml_helper-0.1.0.dist-info/top_level.txt
latex_ml_helper-0.1.0.dist-info/RECORD
