Metadata-Version: 2.1
Name: latex-ml-helper
Version: 0.1.0
Summary: Package for getting latex equations for machine learning models
Home-page: UNKNOWN
Author: Ramal Salha
Author-email: <ramal.salha@gmail.com>
License: UNKNOWN
Keywords: python,video,stream,video stream,camera stream,sockets
Platform: UNKNOWN
Classifier: Development Status :: 1 - Planning
Classifier: Intended Audience :: Developers
Classifier: Programming Language :: Python :: 3
Classifier: Operating System :: Unix
Classifier: Operating System :: MacOS :: MacOS X
Classifier: Operating System :: Microsoft :: Windows
Requires-Dist: pyperclip
